.gitignore
LICENSE
MANIFEST.in
README.md
azure-pipelines.yml
rtd-requirements.txt
setup.py
brian2hears/VERSION
brian2hears/__init__.py
brian2hears/bufferable.py
brian2hears/db.py
brian2hears/erb.py
brian2hears/plotting.py
brian2hears/prefs.py
brian2hears/sounds.py
brian2hears.egg-info/PKG-INFO
brian2hears.egg-info/SOURCES.txt
brian2hears.egg-info/dependency_links.txt
brian2hears.egg-info/not-zip-safe
brian2hears.egg-info/requires.txt
brian2hears.egg-info/top_level.txt
brian2hears/filtering/__init__.py
brian2hears/filtering/dcgc.py
brian2hears/filtering/drnl.py
brian2hears/filtering/filterbank.py
brian2hears/filtering/filterbankgroup.py
brian2hears/filtering/filterbanklibrary.py
brian2hears/filtering/firfilterbank.py
brian2hears/filtering/fractionaldelay.py
brian2hears/filtering/linearfilterbank.py
brian2hears/filtering/tan_carney.py
brian2hears/hrtf/__init__.py
brian2hears/hrtf/hrtf.py
brian2hears/hrtf/ircam.py
brian2hears/hrtf/itd.py
brian2hears/tests/__init__.py
brian2hears/tests/test_db.py
brian2hears/tests/test_filterbank.py
brian2hears/tests/test_hrtf.py
brian2hears/tests/test_sounds.py
debugging/cythonlinearfilterbank.py
debugging/slicing.py
dev/runtests.py
docs_sphinx/Makefile
docs_sphinx/brian.rst
docs_sphinx/buffering.rst
docs_sphinx/conf.py
docs_sphinx/filter_chains.rst
docs_sphinx/hrtf.rst
docs_sphinx/index.rst
docs_sphinx/introduction.rst
docs_sphinx/library.rst
docs_sphinx/make.bat
docs_sphinx/online.rst
docs_sphinx/plotting.rst
docs_sphinx/reference.rst
docs_sphinx/sounds.rst
docs_sphinx/auto_examples/.gitignore
docs_sphinx/auto_examples/IIRfilterbank.ipynb
docs_sphinx/auto_examples/IIRfilterbank.py
docs_sphinx/auto_examples/IIRfilterbank.rst
docs_sphinx/auto_examples/approximate_gammatone.ipynb
docs_sphinx/auto_examples/approximate_gammatone.py
docs_sphinx/auto_examples/approximate_gammatone.rst
docs_sphinx/auto_examples/artificial_vowels.ipynb
docs_sphinx/auto_examples/artificial_vowels.py
docs_sphinx/auto_examples/artificial_vowels.rst
docs_sphinx/auto_examples/auto_examples_jupyter.zip
docs_sphinx/auto_examples/auto_examples_python.zip
docs_sphinx/auto_examples/butterworth.ipynb
docs_sphinx/auto_examples/butterworth.py
