Metadata-Version: 1.2
Name: brian2hears
Version: 0.9.2
Summary: Auditory modelling package for brian2 simulator
Home-page: https://github.com/brian-team/brian2hears
Author: Bertrand Fontaine, Dan Goodman, Marcel Stimberg, Victor Benichoux, Romain Brette
Author-email: team@briansimulator.org
License: UNKNOWN
Platform: UNKNOWN
Classifier: Development Status :: 4 - Beta
Classifier: Intended Audience :: Science/Research
Classifier: License :: OSI Approved :: CEA CNRS Inria Logiciel Libre License, version 2.1 (CeCILL-2.1)
Classifier: Natural Language :: English
Classifier: Operating System :: OS Independent
Classifier: Programming Language :: Python
Classifier: Programming Language :: Python :: 3
Classifier: Topic :: Scientific/Engineering :: Bio-Informatics
Requires-Python: >=3.6
